django_variable/__init__.py
django_variable/apps.py
django_variable/signals.py
django_variable/tests.py
django_variable/utils.py
django_variable/views.py
django_variable/admin/__init__.py
django_variable/admin/configuration.py
django_variable/migrations/0001_initial.py
django_variable/migrations/0002_alter_configuration_options_configuration_file.py
django_variable/migrations/0003_alter_configuration_value.py
django_variable/migrations/__init__.py
django_variable/models/__init__.py
django_variable/models/configuration.py
django_variable-0.1.2.dist-info/LICENSE
django_variable-0.1.2.dist-info/METADATA
django_variable-0.1.2.dist-info/WHEEL
django_variable-0.1.2.dist-info/top_level.txt
django_variable-0.1.2.dist-info/RECORD
