Metadata-Version: 2.1
Name: django-variable
Version: 0.1.2
Summary: Django Variable
Home-page: https://github.com/jeissonp/django-variable
Author: Jeisson Perez Molano
Author-email: jeissonp@gmail.com
Classifier: Framework :: Django
Classifier: Programming Language :: Python
Classifier: Programming Language :: Python :: 3
Classifier: License :: OSI Approved :: MIT License
Classifier: Operating System :: OS Independent
Requires-Python: >=3.8
License-File: LICENSE
Requires-Dist: django>=5
